fold/__init__.py
fold/__main__.py
fold/constants.py
restraint_fold-0.1.4.dist-info/LICENSE
restraint_fold-0.1.4.dist-info/METADATA
restraint_fold-0.1.4.dist-info/WHEEL
restraint_fold-0.1.4.dist-info/top_level.txt
restraint_fold-0.1.4.dist-info/RECORD
