Metadata-Version: 2.1
Name: restraint-fold
Version: 0.1.4
Summary: Simple Protein Structure Parser
Home-page: https://gitee.com/dechin/restraint-fold/
Author: Dechin CHEN
Author-email: dechin.phy@gmail.com
License: MIT License
Platform: any
License-File: LICENSE
Requires-Dist: hadder (==1.7)
Requires-Dist: numpy
